pypdsh/__init__.py
pypdsh/main.py
pypdsh/pypdsh.py
pypdsh-0.1.6.data/data/README.md
pypdsh-0.1.6.dist-info/LICENSE
pypdsh-0.1.6.dist-info/METADATA
pypdsh-0.1.6.dist-info/WHEEL
pypdsh-0.1.6.dist-info/entry_points.txt
pypdsh-0.1.6.dist-info/top_level.txt
pypdsh-0.1.6.dist-info/RECORD
